speedmonitor/__init__.py
speedmonitor/__main__.py
speedmonitor/speedlib.py
speedmonitor/speedtest.py
speedmonitor/views.py
speedmonitor-0.0.7.dist-info/LICENSE.txt
speedmonitor-0.0.7.dist-info/METADATA
speedmonitor-0.0.7.dist-info/WHEEL
speedmonitor-0.0.7.dist-info/top_level.txt
speedmonitor-0.0.7.dist-info/RECORD
