Metadata-Version: 2.1
Name: speedmonitor
Version: 0.0.7
Summary: Monitor internet speed
Home-page: https://github.com/samuelsinayoko/speedmonitor
Author: Sam Sinayoko
License: MIT
Platform: UNKNOWN
Classifier: License :: OSI Approved :: MIT License
Classifier: Programming Language :: Python
Classifier: Programming Language :: Python :: 3
Classifier: Programming Language :: Python :: 3.6
Classifier: Programming Language :: Python :: Implementation :: CPython
Classifier: Programming Language :: Python :: Implementation :: PyPy
Requires-Python: >=3.6.0
Requires-Dist: requests
Requires-Dist: flask
